{
	"status": true,
	"message": "Apps fetched successfully",
	"data": {
		"content": [
			{
				"uid": "37977702-93d5-4ca7-a829-24650cb44c34",
				"group_id": "5c9c6db0-7606-4f9f-9965-5455980881a2",
				"name": "Emmanuel \u0026 Co",
				"support_email": "emmanuel.ainaj@gmail.com",
				"is_disabled": false,
				"endpoints": [],
				"created_at": "2022-03-14T18:56:53.533Z",
				"updated_at": "2022-03-30T11:58:28.163Z",
				"events": 0
			},
			{
				"uid": "1627c837-aaf7-46ee-ab91-ca44d468c8ac",
				"group_id": "5c9c6db0-7606-4f9f-9965-5455980881a2",
				"name": "Company Name",
				"support_email": "emmanuel.ainaj@gmail.com",
				"is_disabled": false,
				"endpoints": [],
				"created_at": "2022-01-21T15:26:06.245Z",
				"updated_at": "2022-01-21T15:26:06.245Z",
				"events": 0
			},
			{
				"uid": "291e98cb-4e93-408f-bb5b-d422ff13d12c",
				"group_id": "5c9c6db0-7606-4f9f-9965-5455980881a2",
				"name": "Testing som",
				"support_email": "emmanuel.ainaj@gmail.com",
				"is_disabled": false,
				"endpoints": [
					{
						"uid": "4d0ab7e0-94ab-4788-9caf-dba9f4789881",
						"target_url": "https://webhook.site/f14ce842-286d-4362-9854-bfe953bfa463",
						"description": "Payment",
						"status": "active",
						"secret": "HQUpvfewhsUC6meLzOsbTrurPq2x672wuQ==",
						"http_timeout": "",
						"rate_limit": 0,
						"rate_limit_duration": "",
						"events": ["payment.test", "payment.new", "payment.update", "payment.trigger"],
						"created_at": "2022-01-21T10:53:35.839Z",
						"updated_at": "2022-01-21T10:53:35.839Z"
					},
					{
						"uid": "8dfc9d70-9733-4876-a0db-5eaae73743ef",
						"target_url": "https://webhook.site/e098aaf6-c605-4cf5-befe-2700f2acfd86",
						"description": "New Crud",
						"status": "active",
						"secret": "U-4aoEpvpSAnYQSGCql-LwiAZE2CRa38sQ==",
						"http_timeout": "",
						"rate_limit": 0,
						"rate_limit_duration": "",
						"events": ["new.test", "new.new"],
						"created_at": "2022-03-22T13:48:32.673Z",
						"updated_at": "2022-03-22T13:48:32.673Z"
					}
				],
				"created_at": "2022-01-21T10:52:31.654Z",
				"updated_at": "2022-03-25T16:33:13.261Z",
				"events": 93
			}
		],
		"pagination": { "total": 3, "page": 1, "perPage": 20, "prev": 0, "next": 0, "totalPage": 1 }
	}
}
